htd_client/__init__.py
htd_client/base_client.py
htd_client/constants.py
htd_client/lync_client.py
htd_client/mca_client.py
htd_client/models.py
htd_client/utils.py
htd_client-0.0.23.dist-info/LICENSE
htd_client-0.0.23.dist-info/METADATA
htd_client-0.0.23.dist-info/WHEEL
htd_client-0.0.23.dist-info/RECORD
