Metadata-Version: 2.1
Name: htd-client
Version: 0.0.23
Summary: A client supporting Home Theater Direct's gateway device.
Home-page: https://github.com/hikirsch/python-htd
License: MIT
Author: Adam Kirschner
Author-email: accounts@adamskirschner.com
Requires-Python: >=3.13,<4.0
Classifier: License :: OSI Approved :: MIT License
Classifier: Programming Language :: Python :: 3
Requires-Dist: pyserial-asyncio (>=0.6,<0.7)
Project-URL: Issues, https://github.com/hikirsch/python-htd/issues
Project-URL: Repository, https://github.com/hikirsch/python-htd
